README.rst
setup.cfg
setup.py
py_round_robin/Round_Robin.py
py_round_robin/__init__.py
py_round_robin.egg-info/PKG-INFO
py_round_robin.egg-info/SOURCES.txt
py_round_robin.egg-info/dependency_links.txt
py_round_robin.egg-info/entry_points.txt
py_round_robin.egg-info/not-zip-safe
py_round_robin.egg-info/requires.txt
py_round_robin.egg-info/top_level.txt