Metadata-Version: 1.1
Name: py-round-robin
Version: 1.4.0
Summary: Round Robin to turn something
Home-page: https://github.com/rfyiamcool/py_round_robin
Author: ruifengyun
Author-email: rfyiamcool@163.com
License: UNKNOWN
Platform: UNKNOWN
Classifier: License :: OSI Approved :: MIT License
Classifier: Programming Language :: Python :: 3.4
